spacecutter/__init__.py
spacecutter/callbacks.py
spacecutter/losses.py
spacecutter/models.py
spacecutter_torch-1.0.0.dist-info/LICENSE
spacecutter_torch-1.0.0.dist-info/METADATA
spacecutter_torch-1.0.0.dist-info/WHEEL
spacecutter_torch-1.0.0.dist-info/RECORD
