Metadata-Version: 2.1
Name: spacecutter-torch
Version: 1.0.0
Summary: Ordinal regression models in PyTorch
License: MIT
Author: Soof Golan
Author-email: pypi@soofgolan.com
Requires-Python: >=3.8,<4.0
Classifier: License :: OSI Approved :: MIT License
Classifier: Programming Language :: Python :: 3
Classifier: Programming Language :: Python :: 3.8
Classifier: Programming Language :: Python :: 3.9
Classifier: Programming Language :: Python :: 3.10
Classifier: Programming Language :: Python :: 3.11
Requires-Dist: torch (>=2.0,<3.0)
